setup.py
hedwig/__init__.py
hedwig/owl/__init__.py
hedwig_owl.egg-info/PKG-INFO
hedwig_owl.egg-info/SOURCES.txt
hedwig_owl.egg-info/dependency_links.txt
hedwig_owl.egg-info/entry_points.txt
hedwig_owl.egg-info/requires.txt
hedwig_owl.egg-info/top_level.txt