Metadata-Version: 1.1
Name: hedwig-owl
Version: 0.1.5
Summary: Hedwig Owl to Send Mails
Home-page: https://github.com/genee-projects/hedwig
Author: Jia Huang
Author-email: iamfat@gmail.com
License: MIT
Keywords: h,e,d,w,i,g
Platform: UNKNOWN
Classifier: Development Status :: 3 - Alpha
Classifier: Intended Audience :: Developers
Classifier: Topic :: Utilities
Classifier: License :: OSI Approved :: MIT License
